{
    "main": {
      "name": "Andrew DeHaven",
      "occupation": "Full-Stack Web Developer",
      "description": "Full-Stack Web Developer",
      "image": "https://media-exp1.licdn.com/dms/image/C4D03AQG0DDx17cccAQ/profile-displayphoto-shrink_800_800/0/1566519968818?e=1618444800&v=beta&t=xPXUOOD_R9b9gxGtDWF7bDg9RC74u8nbkioZPWJAUz4",
      "bio": "My name is Andrew and I am excited to begin this adventure as a junior developer.",
      "contactmessage": "Get in touch with me to receive further details.",
      "email": "dehaven7777@gmail.com",
      "phone": "+01 610 984 7862",
      "address": {
        "city": "Jersey City",
        "state": "New Jersey"
      },
      "resumedownload": "",
      "social": [
        {
          "name": "linkedin",
          "url": "https://www.linkedin.com/jobs/search/?currentJobId=2517797987&pivotType=jymbii",
          "className": "fa fa-linkedin"
        },
        {
          "name": "github",
          "url": "https://github.com/adeha047",
          "className": "fa fa-github"
        }
      ]
    },
    "resume": {
      "skillmessage": "See more details on my download resume link.",
      "education": [
        {
          "school": "Rutgers University",
          "degree": "Certificate in Full Stack Web Development",
          "graduated": "May 2021",
          "description": "A 24-week intensive program focused on gaining technical programming skills in HTML5, CSS3, Javascript, JQuery, Bootstrap, Firebase, Node Js, MySQL, MongoDB, Express, Handelbars.js & ReactJS."
        },
        {
          "school": "Northwestern University",
          "degree": "Masters in Speech Pathology"
        },
        {
          "school": "St. John's University",
          "degree": "Communication Sciences and Disorders",
          "graduated": "May 2016",
          "description":"GPA: 3.95"
        }
      ],
      "work": [
        {
          "company": "eZCom Software",
          "title": " Implementation Specialist/Project Manager",
          "years": "October 2019 - ",
          "description": "Built strong, lasting relationships and strategic partnerships through exceptional client service; served as primary point of contact for client communications"
        },
        {
          "company": "ICS Software",
          "title": "Software Support Specialist",
          "years": "January 2019 - September 2019",
          "description": "Assisted customers on various software related issues including several versions of Windows Operating Systems."
        }, 
        {
            "company": "Computer Aid",
            "title": "IT Infrastructure Administrator/Software Support Tier 1",
            "years": "January 2019 - September 2019",
            "description": "Provided German to English translation on all IT related-issues for employees based in Germany."
          }

      ],
      "skills": [
        {
          "name": "ReactJs"
          
        },
        {
          "name": "CSS"
        },
        {
          "name": "Git"
        },
        {
          "name": "MySQL DB"
        },
        {
          "name": "HTML5"
        },
        {
          "name": "MongoDB"
        }
      ]
    },
    "portfolio": {
      "projects": [
        {
          "title": "The Right Note",
          "category": "Interactive site designed for users to discover more about their favorite artists and the lyrics from that artist. ",
          "image": "https://raw.githubusercontent.com/adeha047/theRightNote/main/music-logo.png",
          "url": " https://adeha047.github.io/theRightNote/"
        },
        {
          "title": "Brewtime App",
          "category": "This full stack application explores making API calls using the Google places/maps API, and geolocation API once a user logs into the website. The user must though allow for location services and then they are provided the closest coffee shops in their location.",
          "image": "coffee.jpg",
          "url": "https://apricot-shortcake-18871.herokuapp.com/"
        },
       
        {
          "title": "Google Book Tracker",
          "category": "React-based Google Books Search app. (html, css, nodejs, expressjs, react, API)",
          "image": "google.jpg",
          "url": "https://reactgooglebooks-search.herokuapp.com/"
        },
        {
          "title": "Burger App",
          "category": "In this app, the user will have the opportunity create a unique burger, eat the burger and then delete the burger from the webpage. The tech used in this app: MySQL, Node.js, Express, and handlebars.",
          "image": "https://icon-library.com/images/hamburger-icon-png/hamburger-icon-png-7.jpg",
          "url": "https://desolate-waters-85761.herokuapp.com/"
        }
      ]
    }
  }